pytest_forward_compatibility.py
pytest_forward_compatibility-0.1.1.dist-info/entry_points.txt
pytest_forward_compatibility-0.1.1.dist-info/LICENSE
pytest_forward_compatibility-0.1.1.dist-info/WHEEL
pytest_forward_compatibility-0.1.1.dist-info/METADATA
pytest_forward_compatibility-0.1.1.dist-info/RECORD
